PyQt5/Qt5/lib/libQt5DataVisualization.so.5
PyQt5/Qt5/qml/QtDataVisualization/libdatavisualizationqml2.so
PyQt5/Qt5/qml/QtDataVisualization/plugins.qmltypes
PyQt5/Qt5/qml/QtDataVisualization/qmldir
PyQt5/Qt5/qml/QtDataVisualization/designer/Bars3DSpecifics.qml
PyQt5/Qt5/qml/QtDataVisualization/designer/Scatter3DSpecifics.qml
PyQt5/Qt5/qml/QtDataVisualization/designer/Surface3DSpecifics.qml
PyQt5/Qt5/qml/QtDataVisualization/designer/qtdatavisualization.metainfo
PyQt5/Qt5/qml/QtDataVisualization/designer/default/Bars3D.qml
PyQt5/Qt5/qml/QtDataVisualization/designer/default/Scatter3D.qml
PyQt5/Qt5/qml/QtDataVisualization/designer/default/Surface3D.qml
PyQt5/Qt5/qml/QtDataVisualization/designer/images/bars3d-icon.png
PyQt5/Qt5/qml/QtDataVisualization/designer/images/bars3d-icon16.png
PyQt5/Qt5/qml/QtDataVisualization/designer/images/scatter3d-icon.png
PyQt5/Qt5/qml/QtDataVisualization/designer/images/scatter3d-icon16.png
PyQt5/Qt5/qml/QtDataVisualization/designer/images/surface3d-icon.png
PyQt5/Qt5/qml/QtDataVisualization/designer/images/surface3d-icon16.png
pyqtdatavisualization_qt5-5.15.18.dist-info/LICENSE
pyqtdatavisualization_qt5-5.15.18.dist-info/METADATA
pyqtdatavisualization_qt5-5.15.18.dist-info/WHEEL
pyqtdatavisualization_qt5-5.15.18.dist-info/RECORD
