Metadata-Version: 2.1
Name: PyQtDataVisualization-Qt5
Version: 5.15.18
Summary: The subset of a Qt installation needed by PyQtDataVisualization.
Home-page: https://www.riverbankcomputing.com/software/pyqt/
Author: Riverbank Computing Limited
Author-email: info@riverbankcomputing.com
License: GPL v3
Platform: Linux
Platform: macOS
Platform: Windows
